nonebot_plugin_nowtime/__init__.py
nonebot_plugin_nowtime/config/nowtime.json
nonebot_plugin_nowtime/config.py
nonebot_plugin_nowtime/resource/time_words.json
nonebot_plugin_nowtime-0.2.0.dist-info/LICENSE
nonebot_plugin_nowtime-0.2.0.dist-info/METADATA
nonebot_plugin_nowtime-0.2.0.dist-info/WHEEL
nonebot_plugin_nowtime-0.2.0.dist-info/RECORD
