Metadata-Version: 2.1
Name: nonebot_plugin_nowtime
Version: 0.2.0
Summary: Nonebot2 plugin for telling the time per hour
Home-page: https://github.com/Cvandia/nonebot_plugin_nowtime
License: MIT
Author: Cvandia
Requires-Python: >=3.9,<4.0
Classifier: License :: OSI Approved :: MIT License
Classifier: Programming Language :: Python :: 3
Classifier: Programming Language :: Python :: 3.9
Classifier: Programming Language :: Python :: 3.10
Classifier: Programming Language :: Python :: 3.11
Classifier: Programming Language :: Python :: 3.12
Requires-Dist: aiofiles (>=0.7.0)
Requires-Dist: httpx (>=0.19.0)
Requires-Dist: nonebot-adapter-onebot (>=2.0.0rc1)
Requires-Dist: nonebot-plugin-apscheduler (>=0.1.3)
Requires-Dist: nonebot2 (>=2.0.0-beta.1)
Requires-Dist: pathlib (>=1.0.1)
Requires-Dist: pydantic (>=1.10.2)
Requires-Dist: ujson (>=5.10.0)
Project-URL: Repository, https://github.com/Cvandia/nonebot_plugin_nowtime
